testcontainers/mysql/__init__.py
tests/test_mysql.py
testcontainers_mysql-0.0.1rc1.dist-info/METADATA
testcontainers_mysql-0.0.1rc1.dist-info/WHEEL
testcontainers_mysql-0.0.1rc1.dist-info/top_level.txt
testcontainers_mysql-0.0.1rc1.dist-info/RECORD
